django_forms_ext-1.2.1.dist-info/licenses/LICENSE
example/sample/__init__.py
example/sample/models.py
example/sample/views.py
forms_ext/__init__.py
forms_ext/fields.py
forms_ext/models.py
forms_ext/validators.py
forms_ext/tests/__init__.py
forms_ext/tests/test_fields.py
forms_ext/tests/test_validators.py
forms_ext/tests/test_views.py
forms_ext/views/__init__.py
forms_ext/views/generic.py
django_forms_ext-1.2.1.dist-info/METADATA
django_forms_ext-1.2.1.dist-info/WHEEL
django_forms_ext-1.2.1.dist-info/top_level.txt
django_forms_ext-1.2.1.dist-info/RECORD
